metapensiero/sqlalchemy/proxy/__init__.py
metapensiero/sqlalchemy/proxy/base.py
metapensiero/sqlalchemy/proxy/core.py
metapensiero/sqlalchemy/proxy/filters.py
metapensiero/sqlalchemy/proxy/json.py
metapensiero/sqlalchemy/proxy/orm.py
metapensiero/sqlalchemy/proxy/pyramid.py
metapensiero/sqlalchemy/proxy/sorters.py
metapensiero/sqlalchemy/proxy/types.py
metapensiero/sqlalchemy/proxy/utils.py
metapensiero_sqlalchemy_proxy-6.0.dist-info/METADATA
metapensiero_sqlalchemy_proxy-6.0.dist-info/WHEEL
metapensiero_sqlalchemy_proxy-6.0.dist-info/entry_points.txt
metapensiero_sqlalchemy_proxy-6.0.dist-info/RECORD
