Metadata-Version: 2.1
Name: metapensiero.sqlalchemy.proxy
Version: 6.0
Summary: Expose SQLAlchemy's queries and their metadata to a webservice
Author-Email: Lele Gaifax <lele@metapensiero.it>
License: GPL-3.0-or-later
Classifier: Programming Language :: Python
Classifier: Programming Language :: Python :: 3 :: Only
Classifier: Programming Language :: Python :: 3
Classifier: Programming Language :: Python :: 3.11
Classifier: Programming Language :: Python :: 3.12
Classifier: Development Status :: 5 - Production/Stable
Classifier: Intended Audience :: Developers
Classifier: License :: OSI Approved :: GNU General Public License v3 or later (GPLv3+)
Classifier: Topic :: Database
Project-URL: Changelog, https://gitlab.com/metapensiero/metapensiero.sqlalchemy.proxy/-/blob/master/CHANGES.rst
Project-URL: Documentation, https://metapensierosqlalchemyproxy.readthedocs.io/en/latest/
Project-URL: Source, https://gitlab.com/metapensiero/metapensiero.sqlalchemy.proxy
Requires-Python: >=3.9
Requires-Dist: sqlalchemy
Requires-Dist: typing-extensions
Provides-Extra: dev
Requires-Dist: build; extra == "dev"
Requires-Dist: bump-my-version; extra == "dev"
Requires-Dist: tomli; extra == "dev"
Requires-Dist: twine; extra == "dev"
Provides-Extra: docs
Requires-Dist: tomli; extra == "docs"
